phoenyx/__init__.py
phoenyx/body.py
phoenyx/button.py
phoenyx/constants.py
phoenyx/errorhandler.py
phoenyx/keys.py
phoenyx/menu.py
phoenyx/opensimplexnoise.py
phoenyx/perlinnoise.py
phoenyx/quadtree.py
phoenyx/renderer.py
phoenyx/sandbox.py
phoenyx/slider.py
phoenyx/test.py
phoenyx/vector.py
phoenyx-0.3.2.dist-info/LICENSE.txt
phoenyx-0.3.2.dist-info/METADATA
phoenyx-0.3.2.dist-info/WHEEL
phoenyx-0.3.2.dist-info/top_level.txt
phoenyx-0.3.2.dist-info/RECORD
