Metadata-Version: 2.1
Name: phoenyx
Version: 0.3.2
Summary: A drawing and physics engine for Pygame
Home-page: https://github.com/ThomasByr/phoenyx.git
Author: Thomas Byr
Author-email: thomas-c2000@outlook.fr
License: UNKNOWN
Platform: UNKNOWN
Classifier: Programming Language :: Python :: 3
Classifier: License :: OSI Approved :: GNU General Public License v3 (GPLv3)
Classifier: Operating System :: OS Independent
Requires-Python: >=3.9
Requires-Dist: pygame
Requires-Dist: pymunk
Requires-Dist: numpy
